{"title":"Introduction","markdown":{"headingText":"Introduction","headingAttr":{"id":"sec-intro","classes":["unnumbered"],"keyvalue":[]},"containsRefs":false,"markdown":"\nIn this section we introduce what Geographic Data Science is. We top it up with a few (optional) further readings for the interested and curious mind.\n\n## **What is *Geographic Data Science*?**\n\nThe following clip is taken from a keynote response by Dani Arribas-Bel at the first [Spatial Data Science Conference](https://carto.com/spatial-data-conference/2017/), organised by [CARTO](https://carto.com/) and held in Brooklyn in 2017. The talk provides a bit of background and context, which will hopefully help you understand a bit better what Geographic Data Science is.\n\nTOP UP with slide content\n\n## **Get ready!**\n\nGo the the Computation Environment section\n\n\n## **Further readings**\n\nTo get a better picture, the following readings complement the overview provided above very well:\n\nBonus\n\nThe chapter is available free online [**`HTML`**](http://shop.oreilly.com/product/0636920028529.do) \\| [**`PDF`**](http://cdn.oreillystatic.com/oreilly/booksamplers/9781449358655_sampler.pdf)\n\n1.  The introductory chapter to \\\"Doing Data Science\\\" [schutt2013doing](https://darribas.org/gds_course/content/bA/concepts_A.html#id1), by Cathy O\\'Neil and Rachel Schutt is general overview of why we needed Data Science and where if came from.\n\n2.  A slightly more technical historical perspective on where Data Science came from and where it might go can be found in David Donoho\\'s recent overview [donoho201750](https://darribas.org/gds_course/content/bA/concepts_A.html#id3).\n\n3.  A geographic take on Data Science, proposing more interaction between Geography and Data Science [singleton2019geographic](https://darribas.org/gds_course/content/bA/concepts_A.html#id5).\n"},"formats":{"html":{"execute":{"fig-width":7,"fig-height":5,"fig-format":"retina","fig-dpi":96,"df-print":"default","error":false,"eval":true,"cache":null,"freeze":false,"echo":true,"output":true,"warning":true,"include":true,"keep-md":false,"keep-ipynb":false,"ipynb":null,"enabled":null,"daemon":null,"daemon-restart":false,"debug":false,"ipynb-filters":[],"engine":"markdown"},"render":{"keep-tex":false,"keep-source":false,"keep-hidden":false,"prefer-html":false,"output-divs":true,"output-ext":"html","fig-align":"default","fig-pos":null,"fig-env":null,"code-fold":"none","code-overflow":"scroll","code-link":false,"code-line-numbers":false,"code-tools":false,"tbl-colwidths":"auto","merge-includes":true,"latex-auto-mk":true,"latex-auto-install":true,"latex-clean":true,"latex-max-runs":10,"latex-makeindex":"makeindex","latex-makeindex-opts":[],"latex-tlmgr-opts":[],"latex-input-paths":[],"latex-output-dir":null,"link-external-icon":false,"link-external-newwindow":false,"self-contained-math":false,"format-resources":[]},"pandoc":{"standalone":true,"wrap":"none","default-image-extension":"png","to":"html","output-file":"intro.html"},"language":{},"metadata":{"lang":"en","fig-responsive":true,"quarto-version":"1.2.269","bibliography":["references.bib"],"editor":"visual","theme":["cosmo","r4gds.scss"]},"extensions":{"book":{"multiFile":true}}},"pdf":{"execute":{"fig-width":5.5,"fig-height":3.5,"fig-format":"pdf","fig-dpi":300,"df-print":"default","error":false,"eval":true,"cache":null,"freeze":false,"echo":true,"output":true,"warning":true,"include":true,"keep-md":false,"keep-ipynb":false,"ipynb":null,"enabled":null,"daemon":null,"daemon-restart":false,"debug":false,"ipynb-filters":[],"engine":"markdown"},"render":{"keep-tex":false,"keep-source":false,"keep-hidden":false,"prefer-html":false,"output-divs":true,"output-ext":"pdf","fig-align":"default","fig-pos":null,"fig-env":null,"code-fold":"none","code-overflow":"scroll","code-link":false,"code-line-numbers":false,"code-tools":false,"tbl-colwidths":true,"merge-includes":true,"latex-auto-mk":true,"latex-auto-install":true,"latex-clean":true,"latex-max-runs":10,"latex-makeindex":"makeindex","latex-makeindex-opts":[],"latex-tlmgr-opts":[],"latex-input-paths":[],"latex-output-dir":null,"link-external-icon":false,"link-external-newwindow":false,"self-contained-math":false,"format-resources":[]},"pandoc":{"pdf-engine":"xelatex","standalone":true,"variables":{"graphics":true,"tables":true},"default-image-extension":"pdf","to":"pdf","output-file":"intro.pdf"},"language":{},"metadata":{"block-headings":true,"bibliography":["references.bib"],"editor":"visual","documentclass":"scrreprt"},"extensions":{"book":{}}}}}